transferlearning/__init__.py
transferlearning/deep/__init__.py
transferlearning/nn/__init__.py
transferlearning/nn/utils.py
transferlearning/traditional/__init__.py
transferlearning/traditional/jda.py
transferlearning-0.0.4.dist-info/DESCRIPTION.rst
transferlearning-0.0.4.dist-info/METADATA
transferlearning-0.0.4.dist-info/RECORD
transferlearning-0.0.4.dist-info/WHEEL
transferlearning-0.0.4.dist-info/metadata.json
transferlearning-0.0.4.dist-info/top_level.txt
